protoxy-0.7.2.dist-info/METADATA
protoxy-0.7.2.dist-info/WHEEL
protoxy-0.7.2.dist-info/licenses/LICENSE
protoxy/errors.py
protoxy/__init__.py
protoxy/_protoxy.cpython-310-aarch64-linux-gnu.so
protoxy-0.7.2.dist-info/RECORD
