Metadata-Version: 2.4
Name: protoxy
Version: 0.7.2
Classifier: Programming Language :: Rust
Classifier: Programming Language :: Python :: Implementation :: CPython
Classifier: Programming Language :: Python :: Implementation :: PyPy
Requires-Dist: protobuf ~=5.27.2
License-File: LICENSE
Summary: A compiler for .proto files into FileDescriptorSets or (experimentally) python dynamic module
Keywords: protobuf,protoc
Maintainer-email: Pierre Tardy <tardyp@gmail.com>
Requires-Python: >=3.8
Project-URL: homepage, https://github.com/tardyp/protoxy
Project-URL: repository, https://github.com/tardyp/protoxy
